continua/__init__.py
continua-0.0.1a1.dist-info/METADATA
continua-0.0.1a1.dist-info/WHEEL
continua-0.0.1a1.dist-info/licenses/LICENSE
continua-0.0.1a1.dist-info/RECORD
